{
  "vendors.js": "/v0.5/static/js/vendors.cf1b9548.js",
  "vendors.js.map": "/v0.5/static/js/vendors.62f381ef1723df55fc43.js.map",
  "components-app-app~components-index~components-layouts-flex-flex~components-layouts-float-float~comp~781ddc62.js": "/v0.5/static/js/components-app-app~components-index~components-layouts-flex-flex~components-layouts-float-float~comp~781ddc62.f773f71a.js",
  "components-app-app~components-index~components-layouts-flex-flex~components-layouts-float-float~comp~781ddc62.js.map": "/v0.5/static/js/components-app-app~components-index~components-layouts-flex-flex~components-layouts-float-float~comp~781ddc62.62f381ef1723df55fc43.js.map",
  "app.js": "/v0.5/static/js/app.abe63b69.js",
  "app.js.map": "/v0.5/static/js/app.62f381ef1723df55fc43.js.map",
  "components-app-app.js": "/v0.5/static/js/components-app-app.6f85d006.js",
  "components-app-app.js.map": "/v0.5/static/js/components-app-app.62f381ef1723df55fc43.js.map",
  "components-index.js": "/v0.5/static/js/components-index.8f1480d1.js",
  "components-index.js.map": "/v0.5/static/js/components-index.62f381ef1723df55fc43.js.map",
  "components-layouts-flex-flex.js": "/v0.5/static/js/components-layouts-flex-flex.7ebab744.js",
  "components-layouts-flex-flex.js.map": "/v0.5/static/js/components-layouts-flex-flex.62f381ef1723df55fc43.js.map",
  "components-layouts-float-float.js": "/v0.5/static/js/components-layouts-float-float.ea6a6331.js",
  "components-layouts-float-float.js.map": "/v0.5/static/js/components-layouts-float-float.62f381ef1723df55fc43.js.map",
  "components-layouts-grid-grid.js": "/v0.5/static/js/components-layouts-grid-grid.a8bc0985.js",
  "components-layouts-grid-grid.js.map": "/v0.5/static/js/components-layouts-grid-grid.62f381ef1723df55fc43.js.map",
  "components-ui-button-button.js": "/v0.5/static/js/components-ui-button-button.cf6f06c4.js",
  "components-ui-button-button.js.map": "/v0.5/static/js/components-ui-button-button.62f381ef1723df55fc43.js.map",
  "components-ui-combobox-combobox.js": "/v0.5/static/js/components-ui-combobox-combobox.8591b61f.js",
  "components-ui-combobox-combobox.js.map": "/v0.5/static/js/components-ui-combobox-combobox.62f381ef1723df55fc43.js.map",
  "components-ui-combotext-combotext.js": "/v0.5/static/js/components-ui-combotext-combotext.b345e2d7.js",
  "components-ui-combotext-combotext.js.map": "/v0.5/static/js/components-ui-combotext-combotext.62f381ef1723df55fc43.js.map",
  "components-ui-label-label.js": "/v0.5/static/js/components-ui-label-label.f7b81b00.js",
  "components-ui-label-label.js.map": "/v0.5/static/js/components-ui-label-label.62f381ef1723df55fc43.js.map",
  "components-ui-link-link.js": "/v0.5/static/js/components-ui-link-link.489e4bd0.js",
  "components-ui-link-link.js.map": "/v0.5/static/js/components-ui-link-link.62f381ef1723df55fc43.js.map",
  "components-ui-menu-menu.js": "/v0.5/static/js/components-ui-menu-menu.ea556b37.js",
  "components-ui-menu-menu.js.map": "/v0.5/static/js/components-ui-menu-menu.62f381ef1723df55fc43.js.map",
  "components-ui-panel-panel.js": "/v0.5/static/js/components-ui-panel-panel.a95116b0.js",
  "components-ui-panel-panel.js.map": "/v0.5/static/js/components-ui-panel-panel.62f381ef1723df55fc43.js.map",
  "components-ui-progress-progress.js": "/v0.5/static/js/components-ui-progress-progress.00049821.js",
  "components-ui-progress-progress.js.map": "/v0.5/static/js/components-ui-progress-progress.62f381ef1723df55fc43.js.map",
  "components-ui-select-select.js": "/v0.5/static/js/components-ui-select-select.dbebb1dd.js",
  "components-ui-select-select.js.map": "/v0.5/static/js/components-ui-select-select.62f381ef1723df55fc43.js.map",
  "components-ui-slider-slider.js": "/v0.5/static/js/components-ui-slider-slider.6960e2bf.js",
  "components-ui-slider-slider.js.map": "/v0.5/static/js/components-ui-slider-slider.62f381ef1723df55fc43.js.map",
  "components-ui-spinner-spinner.js": "/v0.5/static/js/components-ui-spinner-spinner.70f44e25.js",
  "components-ui-spinner-spinner.js.map": "/v0.5/static/js/components-ui-spinner-spinner.62f381ef1723df55fc43.js.map",
  "components-ui-tabs-tabs.js": "/v0.5/static/js/components-ui-tabs-tabs.50d28d21.js",
  "components-ui-tabs-tabs.js.map": "/v0.5/static/js/components-ui-tabs-tabs.62f381ef1723df55fc43.js.map",
  "components-ui-textarea-textarea.js": "/v0.5/static/js/components-ui-textarea-textarea.ef36248c.js",
  "components-ui-textarea-textarea.js.map": "/v0.5/static/js/components-ui-textarea-textarea.62f381ef1723df55fc43.js.map",
  "components-ui-textbox-textbox.js": "/v0.5/static/js/components-ui-textbox-textbox.309c6953.js",
  "components-ui-textbox-textbox.js.map": "/v0.5/static/js/components-ui-textbox-textbox.62f381ef1723df55fc43.js.map",
  "components-ui-tooltip-tooltip.js": "/v0.5/static/js/components-ui-tooltip-tooltip.41fa9224.js",
  "components-ui-tooltip-tooltip.js.map": "/v0.5/static/js/components-ui-tooltip-tooltip.62f381ef1723df55fc43.js.map",
  "components-ui-window-window.js": "/v0.5/static/js/components-ui-window-window.d57a6233.js",
  "components-ui-window-window.js.map": "/v0.5/static/js/components-ui-window-window.62f381ef1723df55fc43.js.map",
  "components-utils-frame-frame.js": "/v0.5/static/js/components-utils-frame-frame.8e652539.js",
  "components-utils-frame-frame.js.map": "/v0.5/static/js/components-utils-frame-frame.62f381ef1723df55fc43.js.map",
  "components-utils-shadow-shadow.js": "/v0.5/static/js/components-utils-shadow-shadow.84d85805.js",
  "components-utils-shadow-shadow.js.map": "/v0.5/static/js/components-utils-shadow-shadow.62f381ef1723df55fc43.js.map",
  "runtime~app.js": "/v0.5/static/js/runtime~app.62f381ef1723df55fc43.js",
  "runtime~app.js.map": "/v0.5/static/js/runtime~app.62f381ef1723df55fc43.js.map",
  "static/js/27.7ec098c2.js": "/v0.5/static/js/27.7ec098c2.js",
  "static/js/27.62f381ef1723df55fc43.js.map": "/v0.5/static/js/27.62f381ef1723df55fc43.js.map",
  "index.html": "/v0.5/index.html"
}